odoo9_addon_sale_sourced_by_line-9.0.1.0.0-py2.7-nspkg.pth
odoo9_addon_sale_sourced_by_line-9.0.1.0.0.dist-info/top_level.txt
odoo9_addon_sale_sourced_by_line-9.0.1.0.0.dist-info/WHEEL
odoo9_addon_sale_sourced_by_line-9.0.1.0.0.dist-info/RECORD
odoo9_addon_sale_sourced_by_line-9.0.1.0.0.dist-info/metadata.json
odoo9_addon_sale_sourced_by_line-9.0.1.0.0.dist-info/DESCRIPTION.rst
odoo9_addon_sale_sourced_by_line-9.0.1.0.0.dist-info/METADATA
odoo9_addon_sale_sourced_by_line-9.0.1.0.0.dist-info/namespace_packages.txt
odoo_addons/sale_sourced_by_line/__openerp__.py
odoo_addons/sale_sourced_by_line/__init__.py
odoo_addons/sale_sourced_by_line/README.rst
odoo_addons/sale_sourced_by_line/view/sale_view.xml
odoo_addons/sale_sourced_by_line/i18n/zh_CN.po
odoo_addons/sale_sourced_by_line/i18n/it.po
odoo_addons/sale_sourced_by_line/i18n/es.po
odoo_addons/sale_sourced_by_line/i18n/sale_sourced_by_line.pot
odoo_addons/sale_sourced_by_line/i18n/sl.po
odoo_addons/sale_sourced_by_line/i18n/de.po
odoo_addons/sale_sourced_by_line/i18n/fr.po
odoo_addons/sale_sourced_by_line/i18n/fi.po
odoo_addons/sale_sourced_by_line/model/stock.py
odoo_addons/sale_sourced_by_line/model/sale.py
odoo_addons/sale_sourced_by_line/model/__init__.py
odoo_addons/sale_sourced_by_line/test/sale_order_source.yml
odoo_addons/sale_sourced_by_line/test/sale_order_multi_source.yml
odoo_addons/sale_sourced_by_line/test/sale_order_not_sourced.yml
odoo_addons/sale_sourced_by_line/tests/test_sale_sourced_by_line.py
odoo_addons/sale_sourced_by_line/tests/__init__.py
odoo_addons/sale_sourced_by_line/tests/test_sale_is_delivered.py
odoo_addons/sale_sourced_by_line/static/description/icon.png
