Metadata-Version: 2.0
Name: odoo9-addon-sale-sourced-by-line
Version: 9.0.1.0.0
Summary: Multiple warehouse source locations for Sale order
Home-page: http://www.camptocamp.com
Author: Camptocamp,Eficent,SerpentCS,Odoo Community Association (OCA)
Author-email: support@odoo-community.org
License: AGPL-3
Platform: UNKNOWN
Requires-Dist: odoo (<9.1a,>=9.0a)
Requires-Dist: odoo9-addon-sale-procurement-group-by-line
Classifier: Programming Language :: Python :: 2.7
Classifier: Framework :: Odoo
Classifier: License :: OSI Approved :: GNU Affero General Public License v3
